kazoo/__init__.py
kazoo/client.py
kazoo/exceptions.py
kazoo/hosts.py
kazoo/interfaces.py
kazoo/loggingsupport.py
kazoo/python2atexit.py
kazoo/retry.py
kazoo/security.py
kazoo/version.py
kazoo/handlers/__init__.py
kazoo/handlers/eventlet.py
kazoo/handlers/gevent.py
kazoo/handlers/threading.py
kazoo/handlers/utils.py
kazoo/protocol/__init__.py
kazoo/protocol/connection.py
kazoo/protocol/paths.py
kazoo/protocol/serialization.py
kazoo/protocol/states.py
kazoo/recipe/__init__.py
kazoo/recipe/barrier.py
kazoo/recipe/counter.py
kazoo/recipe/election.py
kazoo/recipe/lease.py
kazoo/recipe/lock.py
kazoo/recipe/partitioner.py
kazoo/recipe/party.py
kazoo/recipe/queue.py
kazoo/recipe/watchers.py
kazoo/testing/__init__.py
kazoo/testing/common.py
kazoo/testing/harness.py
kazoo/tests/__init__.py
kazoo/tests/test_barrier.py
kazoo/tests/test_build.py
kazoo/tests/test_client.py
kazoo/tests/test_connection.py
kazoo/tests/test_counter.py
kazoo/tests/test_election.py
kazoo/tests/test_eventlet_handler.py
kazoo/tests/test_exceptions.py
kazoo/tests/test_gevent_handler.py
kazoo/tests/test_interrupt.py
kazoo/tests/test_lease.py
kazoo/tests/test_lock.py
kazoo/tests/test_partitioner.py
kazoo/tests/test_party.py
kazoo/tests/test_paths.py
kazoo/tests/test_queue.py
kazoo/tests/test_retry.py
kazoo/tests/test_security.py
kazoo/tests/test_threading_handler.py
kazoo/tests/test_watchers.py
kazoo/tests/util.py
kedo_kazoo-2.2.1.0.1.dist-info/DESCRIPTION.rst
kedo_kazoo-2.2.1.0.1.dist-info/METADATA
kedo_kazoo-2.2.1.0.1.dist-info/RECORD
kedo_kazoo-2.2.1.0.1.dist-info/WHEEL
kedo_kazoo-2.2.1.0.1.dist-info/metadata.json
kedo_kazoo-2.2.1.0.1.dist-info/top_level.txt
